{
  "project_info": {
    "project_number": "198975563507",
    "project_id": "to-do-6ed9f",
    "storage_bucket": "to-do-6ed9f.appspot.com"
  },
  "client": [
    {
      "client_info": {
        "mobilesdk_app_id": "1:198975563507:android:6f956de30916d55a4df986",
        "android_client_info": {
          "package_name": "com.example.todo"
        }
      },
      "oauth_client": [],
      "api_key": [
        {
          "current_key": "AIzaSyBq7V0Ro_M9ef-MKlkTHqN0OYo1MaQdoG4"
        }
      ],
      "services": {
        "appinvite_service": {
          "other_platform_oauth_client": []
        }
      }
    }
  ],
  "configuration_version": "1"
}